[
  {
    "_1": "(Intercept)",
    "estimate_Human": -3.4,
    "estimate_Script": -3.418,
    "estimate_Linguistic": -3.245,
    "estimate_Base": -3.061,
    "std_Error_Human": 0.244,
    "std_Error_Script": 0.279,
    "std_Error_Linguistic": 0.321,
    "std_Error_Base": 0.791,
    "pr_∣_z∣_Human": "<2e-16",
    "pr_∣_z∣_Script": "<2e-16",
    "pr_∣_z∣_Linguistic": "<2e-16",
    "pr_∣_z∣_Base": 0.00011
  },
  {
    "_1": "recency",
    "estimate_Human": 1.322,
    "estimate_Script": 1.322,
    "estimate_Linguistic": 1.324,
    "estimate_Base": 1.322,
    "std_Error_Human": 0.095,
    "std_Error_Script": 0.095,
    "std_Error_Linguistic": 0.096,
    "std_Error_Base": 0.097,
    "pr_∣_z∣_Human": "<2e-16",
    "pr_∣_z∣_Script": "<2e-16",
    "pr_∣_z∣_Linguistic": "<2e-16",
    "pr_∣_z∣_Base": "<2e-16"
  },
  {
    "_1": "frequency",
    "estimate_Human": 0.097,
    "estimate_Script": 0.103,
    "estimate_Linguistic": 0.112,
    "estimate_Base": 0.114,
    "std_Error_Human": 0.098,
    "std_Error_Script": 0.097,
    "std_Error_Linguistic": 0.098,
    "std_Error_Base": 0.102,
    "pr_∣_z∣_Human": 0.317,
    "pr_∣_z∣_Script": 0.289,
    "pr_∣_z∣_Linguistic": 0.251,
    "pr_∣_z∣_Base": 0.262
  },
  {
    "_1": "pastObj",
    "estimate_Human": 0.407,
    "estimate_Script": 0.396,
    "estimate_Linguistic": 0.423,
    "estimate_Base": 0.395,
    "std_Error_Human": 0.293,
    "std_Error_Script": 0.294,
    "std_Error_Linguistic": 0.295,
    "std_Error_Base": 0.3,
    "pr_∣_z∣_Human": 0.165,
    "pr_∣_z∣_Script": 0.178,
    "pr_∣_z∣_Linguistic": 0.151,
    "pr_∣_z∣_Base": 0.189
  },
  {
    "_1": "pastSubj",
    "estimate_Human": -0.967,
    "estimate_Script": -0.973,
    "estimate_Linguistic": -0.909,
    "estimate_Base": -0.926,
    "std_Error_Human": 0.559,
    "std_Error_Script": 0.564,
    "std_Error_Linguistic": 0.562,
    "std_Error_Base": 0.565,
    "pr_∣_z∣_Human": 0.0838,
    "pr_∣_z∣_Script": 0.0846,
    "pr_∣_z∣_Linguistic": 0.106,
    "pr_∣_z∣_Base": 0.101
  },
  {
    "_1": "pastExpPronoun",
    "estimate_Human": 1.603,
    "estimate_Script": 1.619,
    "estimate_Linguistic": 1.616,
    "estimate_Base": 1.602,
    "std_Error_Human": 0.21,
    "std_Error_Script": 0.207,
    "std_Error_Linguistic": 0.208,
    "std_Error_Base": 0.245,
    "pr_∣_z∣_Human": 2.19e-14,
    "pr_∣_z∣_Script": 5.48e-15,
    "pr_∣_z∣_Linguistic": 7.59e-15,
    "pr_∣_z∣_Base": 6.11e-11
  },
  {
    "_1": "depTypeSubj",
    "estimate_Human": 2.939,
    "estimate_Script": 2.942,
    "estimate_Linguistic": 2.656,
    "estimate_Base": 2.417,
    "std_Error_Human": 0.299,
    "std_Error_Script": 0.347,
    "std_Error_Linguistic": 0.429,
    "std_Error_Base": 1.113,
    "pr_∣_z∣_Human": "<2e-16",
    "pr_∣_z∣_Script": "<2e-16",
    "pr_∣_z∣_Linguistic": 5.68e-10,
    "pr_∣_z∣_Base": 0.02994
  },
  {
    "_1": "depTypeObj",
    "estimate_Human": 1.199,
    "estimate_Script": 1.227,
    "estimate_Linguistic": 0.977,
    "estimate_Base": 0.705,
    "std_Error_Human": 0.248,
    "std_Error_Script": 0.306,
    "std_Error_Linguistic": 0.389,
    "std_Error_Base": 1.109,
    "pr_∣_z∣_Human": 1.35e-06,
    "pr_∣_z∣_Script": 6.05e-05,
    "pr_∣_z∣_Linguistic": 0.0119,
    "pr_∣_z∣_Base": 0.525
  },
  {
    "_1": "surprisal",
    "estimate_Human": -0.04,
    "estimate_Script": -0.006,
    "estimate_Linguistic": 0.002,
    "estimate_Base": -0.131,
    "std_Error_Human": 0.099,
    "std_Error_Script": 0.097,
    "std_Error_Linguistic": 0.117,
    "std_Error_Base": 0.387,
    "pr_∣_z∣_Human": 0.684,
    "pr_∣_z∣_Script": 0.951,
    "pr_∣_z∣_Linguistic": 0.988,
    "pr_∣_z∣_Base": 0.735
  },
  {
    "_1": "residualEntropy",
    "estimate_Human": -0.009,
    "estimate_Script": 0.023,
    "estimate_Linguistic": -0.141,
    "estimate_Base": -0.128,
    "std_Error_Human": 0.088,
    "std_Error_Script": 0.128,
    "std_Error_Linguistic": 0.168,
    "std_Error_Base": 0.258,
    "pr_∣_z∣_Human": 0.916,
    "pr_∣_z∣_Script": 0.859,
    "pr_∣_z∣_Linguistic": 0.401,
    "pr_∣_z∣_Base": 0.619
  }
]
