[
  {
    "_1": "",
    "Ntrain=5000_No_Char": "",
    "Ntrain=5000_mimick": "",
    "Ntrain=5000_char": "→tag",
    "Ntrain=5000_Both": "",
    "full_data_Ntrain": "",
    "full_data_No_Char": "",
    "full_data_mimick": "",
    "full_data_char": "→tag",
    "both": "",
    "pSG": 2016
  },
  {
    "_1": "kk",
    "Ntrain=5000_No_Char": "—",
    "Ntrain=5000_mimick": "—",
    "Ntrain=5000_char": "—",
    "Ntrain=5000_Both": "—",
    "full_data_Ntrain": 4949,
    "full_data_No_Char": 81.94,
    "full_data_mimick": 83.95,
    "full_data_char": 83.64,
    "both": 84.88,
    "pSG": ""
  },
  {
    "_1": "ta",
    "Ntrain=5000_No_Char": 82.3,
    "Ntrain=5000_mimick": 81.55,
    "Ntrain=5000_char": 84.97,
    "Ntrain=5000_Both": 85.22,
    "full_data_Ntrain": 6329,
    "full_data_No_Char": 80.44,
    "full_data_mimick": 82.96,
    "full_data_char": 84.11,
    "both": 84.46,
    "pSG": ""
  },
  {
    "_1": "lv",
    "Ntrain=5000_No_Char": 80.44,
    "Ntrain=5000_mimick": 84.32,
    "Ntrain=5000_char": 84.49,
    "Ntrain=5000_Both": 85.91,
    "full_data_Ntrain": 13781,
    "full_data_No_Char": 85.77,
    "full_data_mimick": 87.95,
    "full_data_char": 89.55,
    "both": 89.99,
    "pSG": ""
  },
  {
    "_1": "vi",
    "Ntrain=5000_No_Char": 85.67,
    "Ntrain=5000_mimick": 84.22,
    "Ntrain=5000_char": 84.85,
    "Ntrain=5000_Both": 85.43,
    "full_data_Ntrain": 31800,
    "full_data_No_Char": 89.94,
    "full_data_mimick": 90.34,
    "full_data_char": 90.5,
    "both": 90.19,
    "pSG": ""
  },
  {
    "_1": "hu",
    "Ntrain=5000_No_Char": 82.88,
    "Ntrain=5000_mimick": 88.93,
    "Ntrain=5000_char": 85.83,
    "Ntrain=5000_Both": 88.34,
    "full_data_Ntrain": 33017,
    "full_data_No_Char": 91.52,
    "full_data_mimick": 93.88,
    "full_data_char": 94.07,
    "both": 93.74,
    "pSG": ""
  },
  {
    "_1": "tr",
    "Ntrain=5000_No_Char": 83.69,
    "Ntrain=5000_mimick": 85.6,
    "Ntrain=5000_char": 84.23,
    "Ntrain=5000_Both": 86.25,
    "full_data_Ntrain": 41748,
    "full_data_No_Char": 90.19,
    "full_data_mimick": 91.82,
    "full_data_char": 93.11,
    "both": 92.68,
    "pSG": ""
  },
  {
    "_1": "el",
    "Ntrain=5000_No_Char": 93.1,
    "Ntrain=5000_mimick": 93.63,
    "Ntrain=5000_char": 94.05,
    "Ntrain=5000_Both": 94.64,
    "full_data_Ntrain": 47449,
    "full_data_No_Char": 97.27,
    "full_data_mimick": 98.08,
    "full_data_char": 98.09,
    "both": 98.22,
    "pSG": ""
  },
  {
    "_1": "bg",
    "Ntrain=5000_No_Char": 90.97,
    "Ntrain=5000_mimick": 93.16,
    "Ntrain=5000_char": 93.03,
    "Ntrain=5000_Both": 93.52,
    "full_data_Ntrain": 50000,
    "full_data_No_Char": 96.63,
    "full_data_mimick": 97.29,
    "full_data_char": 97.95,
    "both": 97.78,
    "pSG": 98.23
  },
  {
    "_1": "sv",
    "Ntrain=5000_No_Char": 90.87,
    "Ntrain=5000_mimick": 92.3,
    "Ntrain=5000_char": 92.27,
    "Ntrain=5000_Both": 93.02,
    "full_data_Ntrain": 66645,
    "full_data_No_Char": 95.26,
    "full_data_mimick": 96.27,
    "full_data_char": 96.69,
    "both": 96.87,
    "pSG": 96.6
  },
  {
    "_1": "eu",
    "Ntrain=5000_No_Char": 82.67,
    "Ntrain=5000_mimick": 84.44,
    "Ntrain=5000_char": 86.01,
    "Ntrain=5000_Both": 86.93,
    "full_data_Ntrain": 72974,
    "full_data_No_Char": 91.67,
    "full_data_mimick": 93.16,
    "full_data_char": 94.46,
    "both": 94.29,
    "pSG": 95.38
  },
  {
    "_1": "ru",
    "Ntrain=5000_No_Char": 87.4,
    "Ntrain=5000_mimick": 89.72,
    "Ntrain=5000_char": 88.65,
    "Ntrain=5000_Both": 90.91,
    "full_data_Ntrain": 79772,
    "full_data_No_Char": 92.59,
    "full_data_mimick": 95.21,
    "full_data_char": 95.98,
    "both": 95.84,
    "pSG": ""
  },
  {
    "_1": "da",
    "Ntrain=5000_No_Char": 89.46,
    "Ntrain=5000_mimick": 90.13,
    "Ntrain=5000_char": 89.96,
    "Ntrain=5000_Both": 90.55,
    "full_data_Ntrain": 88980,
    "full_data_No_Char": 94.14,
    "full_data_mimick": 95.04,
    "full_data_char": 96.13,
    "both": 96.02,
    "pSG": 96.16
  },
  {
    "_1": "id",
    "Ntrain=5000_No_Char": 89.07,
    "Ntrain=5000_mimick": 89.34,
    "Ntrain=5000_char": 89.81,
    "Ntrain=5000_Both": 90.21,
    "full_data_Ntrain": 97531,
    "full_data_No_Char": 92.92,
    "full_data_mimick": 93.24,
    "full_data_char": 93.41,
    "both": 93.7,
    "pSG": 93.32
  },
  {
    "_1": "zh",
    "Ntrain=5000_No_Char": 80.84,
    "Ntrain=5000_mimick": 85.69,
    "Ntrain=5000_char": 81.84,
    "Ntrain=5000_Both": 85.53,
    "full_data_Ntrain": 98608,
    "full_data_No_Char": 90.91,
    "full_data_mimick": 93.31,
    "full_data_char": 93.36,
    "both": 93.72,
    "pSG": ""
  },
  {
    "_1": "fa",
    "Ntrain=5000_No_Char": 93.5,
    "Ntrain=5000_mimick": 93.58,
    "Ntrain=5000_char": 93.53,
    "Ntrain=5000_Both": 93.71,
    "full_data_Ntrain": 121064,
    "full_data_No_Char": 96.77,
    "full_data_mimick": 97.03,
    "full_data_char": 97.2,
    "both": 97.16,
    "pSG": 97.6
  },
  {
    "_1": "he",
    "Ntrain=5000_No_Char": 90.73,
    "Ntrain=5000_mimick": 91.69,
    "Ntrain=5000_char": 91.93,
    "Ntrain=5000_Both": 91.7,
    "full_data_Ntrain": 135496,
    "full_data_No_Char": 95.65,
    "full_data_mimick": 96.15,
    "full_data_char": 96.59,
    "both": 96.37,
    "pSG": 96.62
  },
  {
    "_1": "ro",
    "Ntrain=5000_No_Char": 87.73,
    "Ntrain=5000_mimick": 89.18,
    "Ntrain=5000_char": 88.96,
    "Ntrain=5000_Both": 89.38,
    "full_data_Ntrain": 163262,
    "full_data_No_Char": 95.68,
    "full_data_mimick": 96.72,
    "full_data_char": 97.07,
    "both": 97.09,
    "pSG": ""
  },
  {
    "_1": "en",
    "Ntrain=5000_No_Char": 87.48,
    "Ntrain=5000_mimick": 88.45,
    "Ntrain=5000_char": 88.89,
    "Ntrain=5000_Both": 88.89,
    "full_data_Ntrain": 204587,
    "full_data_No_Char": 93.39,
    "full_data_mimick": 94.04,
    "full_data_char": 94.9,
    "both": 94.7,
    "pSG": 95.17
  },
  {
    "_1": "ar",
    "Ntrain=5000_No_Char": 89.01,
    "Ntrain=5000_mimick": 90.58,
    "Ntrain=5000_char": 90.49,
    "Ntrain=5000_Both": 90.62,
    "full_data_Ntrain": 225853,
    "full_data_No_Char": 95.51,
    "full_data_mimick": 95.72,
    "full_data_char": 96.37,
    "both": 96.24,
    "pSG": 98.87
  },
  {
    "_1": "hi",
    "Ntrain=5000_No_Char": 87.89,
    "Ntrain=5000_mimick": 87.77,
    "Ntrain=5000_char": 87.92,
    "Ntrain=5000_Both": 88.09,
    "full_data_Ntrain": 281057,
    "full_data_No_Char": 96.31,
    "full_data_mimick": 96.45,
    "full_data_char": 96.64,
    "both": 96.61,
    "pSG": 96.97
  },
  {
    "_1": "it",
    "Ntrain=5000_No_Char": 91.35,
    "Ntrain=5000_mimick": 92.5,
    "Ntrain=5000_char": 92.45,
    "Ntrain=5000_Both": 93.01,
    "full_data_Ntrain": 289440,
    "full_data_No_Char": 97.22,
    "full_data_mimick": 97.47,
    "full_data_char": 97.76,
    "both": 97.69,
    "pSG": 97.9
  },
  {
    "_1": "es",
    "Ntrain=5000_No_Char": 90.54,
    "Ntrain=5000_mimick": 91.41,
    "Ntrain=5000_char": 91.71,
    "Ntrain=5000_Both": 91.78,
    "full_data_Ntrain": 382436,
    "full_data_No_Char": 94.68,
    "full_data_mimick": 94.84,
    "full_data_char": 95.08,
    "both": 95.05,
    "pSG": 95.67
  },
  {
    "_1": "cs",
    "Ntrain=5000_No_Char": 87.97,
    "Ntrain=5000_mimick": 90.81,
    "Ntrain=5000_char": 90.17,
    "Ntrain=5000_Both": 91.29,
    "full_data_Ntrain": 1173282,
    "full_data_No_Char": 96.34,
    "full_data_mimick": 97.62,
    "full_data_char": 98.18,
    "both": 97.93,
    "pSG": 98.02
  }
]
