[
  {
    "_Genre": "Fiction",
    "_CBOW": 67.5,
    "_ESIM": 73.0,
    "_InnerAtt": 73.2
  },
  {
    "_Genre": "Government",
    "_CBOW": 67.5,
    "_ESIM": 74.8,
    "_InnerAtt": 75.2
  },
  {
    "_Genre": "Slate",
    "_CBOW": 60.6,
    "_ESIM": 67.9,
    "_InnerAtt": 67.2
  },
  {
    "_Genre": "Telephone",
    "_CBOW": 63.7,
    "_ESIM": 72.2,
    "_InnerAtt": 73.0
  },
  {
    "_Genre": "Travel",
    "_CBOW": 64.6,
    "_ESIM": 73.7,
    "_InnerAtt": 72.8
  },
  {
    "_Genre": "9/11",
    "_CBOW": 63.2,
    "_ESIM": 71.9,
    "_InnerAtt": 70.5
  },
  {
    "_Genre": "Face-to-face",
    "_CBOW": 66.3,
    "_ESIM": 71.2,
    "_InnerAtt": 74.5
  },
  {
    "_Genre": "Letters",
    "_CBOW": 68.3,
    "_ESIM": 74.7,
    "_InnerAtt": 75.4
  },
  {
    "_Genre": "Oup",
    "_CBOW": 62.8,
    "_ESIM": 71.7,
    "_InnerAtt": 71.5
  },
  {
    "_Genre": "Verbatim",
    "_CBOW": 62.7,
    "_ESIM": 71.9,
    "_InnerAtt": 69.5
  },
  {
    "_Genre": " MultiNLI Overall",
    "_CBOW": 64.7,
    "_ESIM": 72.2,
    "_InnerAtt": 72.3
  }
]
