[
  {
    "num_encoders": "encoder type",
    "2": "B-LSTM"
  },
  {
    "num_encoders": "encoder layers",
    "2": 2
  },
  {
    "num_encoders": "encoder hidden dim",
    "2": 500
  },
  {
    "num_encoders": "# decoders",
    "2": 1
  },
  {
    "num_encoders": "decoder type",
    "2": "LSTM"
  },
  {
    "num_encoders": "decoder layers",
    "2": 2
  },
  {
    "num_encoders": "decoder hidden dim",
    "2": 500
  },
  {
    "num_encoders": "word vector dim",
    "2": 300
  },
  {
    "num_encoders": "attention type",
    "2": " general"
  },
  {
    "num_encoders": "dropout",
    "2": 0.3
  },
  {
    "num_encoders": "beam size",
    "2": 5
  }
]
