[
  {
    "_Model": " Indirect:   O(  n2)",
    "_TE3‡_P": "",
    "_TE3‡_R": "",
    "_TE3‡_F": "",
    "_TD‡_P": "",
    "_TD‡_R": "",
    "_TD‡_F": ""
  },
  {
    "_Model": "TL2RTL (  Lτ)",
    "_TE3‡_P": 53.5,
    "_TE3‡_R": 51.1,
    "_TE3‡_F": 52.3,
    "_TD‡_P": 59.1,
    "_TD‡_R": 61.2,
    "_TD‡_F": 60.1
  },
  {
    "_Model": "TL2RTL (  Lτce)",
    "_TE3‡_P": 53.9,
    "_TE3‡_R": 51.7,
    "_TE3‡_F": 52.8,
    "_TD‡_P": 61.2,
    "_TD‡_R": 60.7,
    "_TD‡_F": 60.9
  },
  {
    "_Model": "TL2RTL (  Lτh)",
    "_TE3‡_P": 52.8,
    "_TE3‡_R": 51.1,
    "_TE3‡_F": 51.9,
    "_TD‡_P": 57.9,
    "_TD‡_R": 60.6,
    "_TD‡_F": 59.2
  },
  {
    "_Model": "TL2RTL (  L∗)",
    "_TE3‡_P": 52.6,
    "_TE3‡_R": 52.0,
    "_TE3‡_F": 52.3,
    "_TD‡_P": 62.3,
    "_TD‡_R": 62.3,
    "_TD‡_F": 62.3
  },
  {
    "_Model": " Direct:   O(  n)",
    "_TE3‡_P": "",
    "_TE3‡_R": "",
    "_TE3‡_F": "",
    "_TD‡_P": "",
    "_TD‡_R": "",
    "_TD‡_F": ""
  },
  {
    "_Model": "S-TLM (  Lτ)",
    "_TE3‡_P": 50.1,
    "_TE3‡_R": 50.4,
    "_TE3‡_F": 50.2,
    "_TD‡_P": 57.8,
    "_TD‡_R": 59.5,
    "_TD‡_F": 58.6
  },
  {
    "_Model": "S-TLM (  Lτce)",
    "_TE3‡_P": 50.1,
    "_TE3‡_R": 50.0,
    "_TE3‡_F": 50.1,
    "_TD‡_P": 53.4,
    "_TD‡_R": 53.5,
    "_TD‡_F": 53.5
  },
  {
    "_Model": "S-TLM (  Lτh)",
    "_TE3‡_P": 51.5,
    "_TE3‡_R": 51.7,
    "_TE3‡_F": 51.6,
    "_TD‡_P": 55.1,
    "_TD‡_R": 56.4,
    "_TD‡_F": 55.7
  },
  {
    "_Model": "S-TLM (  L∗)",
    "_TE3‡_P": 50.9,
    "_TE3‡_R": 51.0,
    "_TE3‡_F": 51.0,
    "_TD‡_P": 56.5,
    "_TD‡_R": 55.3,
    "_TD‡_F": 55.9
  },
  {
    "_Model": "C-TLM (  Lτ)",
    "_TE3‡_P": 56.2,
    "_TE3‡_R": 56.1,
    "_TE3‡_F": 56.1,
    "_TD‡_P": 57.1,
    "_TD‡_R": 59.7,
    "_TD‡_F": 58.4
  },
  {
    "_Model": "C-TLM (  Lτce)",
    "_TE3‡_P": 54.4,
    "_TE3‡_R": 55.4,
    "_TE3‡_F": 54.9,
    "_TD‡_P": 52.4,
    "_TD‡_R": 57.3,
    "_TD‡_F": 54.7
  },
  {
    "_Model": "C-TLM (  Lτh)",
    "_TE3‡_P": 55.7,
    "_TE3‡_R": 55.5,
    "_TE3‡_F": 55.6,
    "_TD‡_P": 55.3,
    "_TD‡_R": 54.9,
    "_TD‡_F": 55.1
  },
  {
    "_Model": "C-TLM (  L∗)",
    "_TE3‡_P": 54.0,
    "_TE3‡_R": 54.3,
    "_TE3‡_F": 54.1,
    "_TD‡_P": 54.6,
    "_TD‡_R": 53.5,
    "_TD‡_F": 54.1
  }
]
