[
  {
    "threshold": "Neutral Sentiment",
    "0_50": 10,
    "0_66": 70,
    "0_75": 95,
    "0_90": 234
  },
  {
    "threshold": "Flipped Sentiment",
    "0_50": 15,
    "0_66": 4,
    "0_75": 2,
    "0_90": 0
  },
  {
    "threshold": "Fleiss’ Kappa (  κ)",
    "0_50": 0.38,
    "0_66": 0.42,
    "0_75": 0.44,
    "0_90": 0.58
  },
  {
    "threshold": "no-distill, no-project",
    "0_50": 81.32,
    "0_66": 83.54,
    "0_75": 84.54,
    "0_90": 87.55
  },
  {
    "threshold": "ELMo, no-project",
    "0_50": 87.56,
    "0_66": 90.0,
    "0_75": 91.31,
    "0_90": 93.14
  }
]