[
  {
    "_1": "majority",
    "p": 32.9,
    "r": 50.0,
    "f1": 39.7
  },
  {
    "_1": "coin-toss",
    "p": 50.4,
    "r": 50.5,
    "f1": 49.1
  },
  {
    "_1": " Non-Anonymized",
    "p": " Non-Anonymized",
    "r": " Non-Anonymized",
    "f1": " Non-Anonymized"
  },
  {
    "_1": "bow-svm",
    "p": 71.5,
    "r": 72.0,
    "f1": 71.8
  },
  {
    "_1": "bigru-att",
    "p": 87.1,
    "r": 77.2,
    "f1": 79.5
  },
  {
    "_1": "han",
    "p": 88.2,
    "r": 78.0,
    "f1": 80.5
  },
  {
    "_1": "bert",
    "p": 24.0,
    "r": 50.0,
    "f1": 17.0
  },
  {
    "_1": "hier-bert",
    "p": 90.4,
    "r": 79.3,
    "f1": 82.0
  },
  {
    "_1": " Anonymized",
    "p": " Anonymized",
    "r": " Anonymized",
    "f1": " Anonymized"
  },
  {
    "_1": "bow-svm",
    "p": 71.6,
    "r": 70.5,
    "f1": 70.9
  },
  {
    "_1": "bigru-att",
    "p": 87.0,
    "r": 76.6,
    "f1": 78.9
  },
  {
    "_1": "han",
    "p": 85.2,
    "r": 78.3,
    "f1": 80.2
  },
  {
    "_1": "bert",
    "p": 17.0,
    "r": 50.0,
    "f1": 25.4
  },
  {
    "_1": "hier-bert",
    "p": 85.2,
    "r": 78.1,
    "f1": 80.1
  }
]
