[
  {
    "Model": "Baseline (BL)",
    "CNN_full": " full: 19.7 dict: 56.0",
    "CNN_dict": " full: 19.7 dict: 56.0",
    "CNN_list": " full: 19.7 dict: 56.0",
    "CNN_k": " full: 19.7 dict: 56.0",
    "CNN_MRR": " full: 19.7 dict: 56.0",
    "LSTM_full": " full: 17.9",
    "LSTM_list": " full: 17.9",
    "LSTM_k": " full: 17.9",
    "LSTM_MRR": " full: 17.9"
  },
  {
    "Model": "BL+ Glove (Jeffrey:14)",
    "CNN_full": 22.0,
    "CNN_dict": 62.5,
    "CNN_list": 75.8,
    "CNN_k": 7,
    "CNN_MRR": 44.5,
    "LSTM_full": 19.1,
    "LSTM_list": 75.3,
    "LSTM_k": 4,
    "LSTM_MRR": 78.8
  },
  {
    "Model": "BL+C-LSTM (Chunting:15)",
    "CNN_full": 21.4,
    "CNN_dict": 61.0,
    "CNN_list": 71.3,
    "CNN_k": 8,
    "CNN_MRR": 45.6,
    "LSTM_full": 18.9,
    "LSTM_list": 74.7,
    "LSTM_k": 4,
    "LSTM_MRR": 80.7
  },
  {
    "Model": "BL+CNN-RNN (Xingyou:16)",
    "CNN_full": 21.7,
    "CNN_dict": 61.8,
    "CNN_list": 73.3,
    "CNN_k": 8,
    "CNN_MRR": 44.5,
    "LSTM_full": 19.5,
    "LSTM_list": 77.1,
    "LSTM_k": 4,
    "LSTM_MRR": 80.9
  },
  {
    "Model": "BL+MVCNN (Wenpeng:16)",
    "CNN_full": 21.3,
    "CNN_dict": 60.6,
    "CNN_list": 71.9,
    "CNN_k": 8,
    "CNN_MRR": 44.2,
    "LSTM_full": 19.2,
    "LSTM_list": 75.8,
    "LSTM_k": 4,
    "LSTM_MRR": 78.8
  },
  {
    "Model": "BL+Attentive LSTM (Ming:16)",
    "CNN_full": 21.9,
    "CNN_dict": 62.4,
    "CNN_list": 74.0,
    "CNN_k": 8,
    "CNN_MRR": 45.7,
    "LSTM_full": 19.1,
    "LSTM_list": 71.4,
    "LSTM_k": 5,
    "LSTM_MRR": 80.2
  },
  {
    "Model": "BL+fasttext (Armand:17)",
    "CNN_full": 21.9,
    "CNN_dict": 62.2,
    "CNN_list": 75.4,
    "CNN_k": 7,
    "CNN_MRR": 44.6,
    "LSTM_full": 19.4,
    "LSTM_list": 76.1,
    "LSTM_k": 4,
    "LSTM_MRR": 80.3
  },
  {
    "Model": "BL+InferSent (Alexis:17)",
    "CNN_full": 22.0,
    "CNN_dict": 62.5,
    "CNN_list": 75.8,
    "CNN_k": 7,
    "CNN_MRR": 44.5,
    "LSTM_full": 19.4,
    "LSTM_list": 76.7,
    "LSTM_k": 4,
    "LSTM_MRR": 79.7
  },
  {
    "Model": "BL+USE-T (Daniel:18)",
    "CNN_full": 22.0,
    "CNN_dict": 62.5,
    "CNN_list": 78.3,
    "CNN_k": 6,
    "CNN_MRR": 44.7,
    "LSTM_full": 19.2,
    "LSTM_list": 75.8,
    "LSTM_k": 4,
    "LSTM_MRR": 79.5
  },
  {
    "Model": "BL+TWE (Ahmed:18)",
    "CNN_full": 22.2,
    "CNN_dict": 63.0,
    "CNN_list": 76.3,
    "CNN_k": 7,
    "CNN_MRR": 44.7,
    "LSTM_full": 19.5,
    "LSTM_list": 76.7,
    "LSTM_k": 4,
    "LSTM_MRR": 80.2
  },
  {
    "Model": "BL+FDCLSTM (ours)",
    "CNN_full": 22.3,
    "CNN_dict": 63.3,
    "CNN_list": 75.1,
    "CNN_k": 8,
    "CNN_MRR": 45.0,
    "LSTM_full": 20.2,
    "LSTM_list": 67.9,
    "LSTM_k": 9,
    "LSTM_MRR": 79.8
  },
  {
    "Model": "BL+FDCLSTM  AT (ours)",
    "CNN_full": 22.4,
    "CNN_dict": 63.7,
    "CNN_list": 75.5,
    "CNN_k": 8,
    "CNN_MRR": 45.9,
    "LSTM_full": 20.1,
    "LSTM_list": 67.6,
    "LSTM_k": 9,
    "LSTM_MRR": 81.8
  },
  {
    "Model": "BL+FDCLSTM  lexicon (ours)",
    "CNN_full": 22.6,
    "CNN_dict": 64.3,
    "CNN_list": 76.3,
    "CNN_k": 8,
    "CNN_MRR": 45.1,
    "LSTM_full": 19.4,
    "LSTM_list": 76.4,
    "LSTM_k": 4,
    "LSTM_MRR": 78.8
  },
  {
    "Model": "BL+FDCLSTM  AT+  lexicon (ours)",
    "CNN_full": 22.6,
    "CNN_dict": 64.3,
    "CNN_list": 76.3,
    "CNN_k": 8,
    "CNN_MRR": 45.1,
    "LSTM_full": 19.7,
    "LSTM_list": 77.8,
    "LSTM_k": 4,
    "LSTM_MRR": 80.4
  }
]
