[
  {
    "test_Condition": "Seen Pairings",
    "Cosine_Similarity_±_SD_↑_RGB": 0.954,
    "Cosine_Similarity_±_SD_↑_WM18": 0.953,
    "Cosine_Similarity_±_SD_↑_HSV": 0.934,
    "Cosine_Similarity_±_SD_↑_Ensemble": 0.954,
    "Cosine_Similarity_±_SD_↑_WM18∗": 0.68
  },
  {
    "test_Condition": "Unseen Pairings",
    "Cosine_Similarity_±_SD_↑_RGB": 0.799,
    "Cosine_Similarity_±_SD_↑_WM18": 0.771,
    "Cosine_Similarity_±_SD_↑_HSV": 0.843,
    "Cosine_Similarity_±_SD_↑_Ensemble": 0.797,
    "Cosine_Similarity_±_SD_↑_WM18∗": 0.68
  },
  {
    "test_Condition": "Unseen Ref. Color",
    "Cosine_Similarity_±_SD_↑_RGB": 0.781,
    "Cosine_Similarity_±_SD_↑_WM18": 0.767,
    "Cosine_Similarity_±_SD_↑_HSV": 0.945,
    "Cosine_Similarity_±_SD_↑_Ensemble": 0.804,
    "Cosine_Similarity_±_SD_↑_WM18∗": 0.4
  },
  {
    "test_Condition": "Unseen Modifiers",
    "Cosine_Similarity_±_SD_↑_RGB": 0.633,
    "Cosine_Similarity_±_SD_↑_WM18": 0.637,
    "Cosine_Similarity_±_SD_↑_HSV": 0.724,
    "Cosine_Similarity_±_SD_↑_Ensemble": 0.629,
    "Cosine_Similarity_±_SD_↑_WM18∗": 0.41
  },
  {
    "test_Condition": "Fully Unseen",
    "Cosine_Similarity_±_SD_↑_RGB": 0.37,
    "Cosine_Similarity_±_SD_↑_WM18": 0.358,
    "Cosine_Similarity_±_SD_↑_HSV": 0.919,
    "Cosine_Similarity_±_SD_↑_Ensemble": 0.445,
    "Cosine_Similarity_±_SD_↑_WM18∗": -0.21
  },
  {
    "test_Condition": "Overall",
    "Cosine_Similarity_±_SD_↑_RGB": 0.858,
    "Cosine_Similarity_±_SD_↑_WM18": 0.856,
    "Cosine_Similarity_±_SD_↑_HSV": 0.911,
    "Cosine_Similarity_±_SD_↑_Ensemble": 0.868,
    "Cosine_Similarity_±_SD_↑_WM18∗": 0.65
  },
  {
    "test_Condition": "",
    "Cosine_Similarity_±_SD_↑_RGB": " Delta-E ± SD  (↓)",
    "Cosine_Similarity_±_SD_↑_WM18": " Delta-E ± SD  (↓)",
    "Cosine_Similarity_±_SD_↑_HSV": " Delta-E ± SD  (↓)",
    "Cosine_Similarity_±_SD_↑_Ensemble": " Delta-E ± SD  (↓)",
    "Cosine_Similarity_±_SD_↑_WM18∗": " Delta-E ± SD  (↓)"
  },
  {
    "test_Condition": "Test Condition",
    "Cosine_Similarity_±_SD_↑_RGB": "RGB",
    "Cosine_Similarity_±_SD_↑_WM18": "WM18",
    "Cosine_Similarity_±_SD_↑_HSV": "HSV",
    "Cosine_Similarity_±_SD_↑_Ensemble": "Ensemble",
    "Cosine_Similarity_±_SD_↑_WM18∗": "WM18"
  },
  {
    "test_Condition": "Seen Pairings",
    "Cosine_Similarity_±_SD_↑_RGB": 3.121,
    "Cosine_Similarity_±_SD_↑_WM18": 3.188,
    "Cosine_Similarity_±_SD_↑_HSV": 5.38,
    "Cosine_Similarity_±_SD_↑_Ensemble": 4.093,
    "Cosine_Similarity_±_SD_↑_WM18∗": 6.1
  },
  {
    "test_Condition": "Unseen Pairings",
    "Cosine_Similarity_±_SD_↑_RGB": 6.454,
    "Cosine_Similarity_±_SD_↑_WM18": 6.825,
    "Cosine_Similarity_±_SD_↑_HSV": 11.701,
    "Cosine_Similarity_±_SD_↑_Ensemble": 5.873,
    "Cosine_Similarity_±_SD_↑_WM18∗": 7.9
  },
  {
    "test_Condition": "Unseen Ref. Color",
    "Cosine_Similarity_±_SD_↑_RGB": 7.456,
    "Cosine_Similarity_±_SD_↑_WM18": 7.658,
    "Cosine_Similarity_±_SD_↑_HSV": 10.429,
    "Cosine_Similarity_±_SD_↑_Ensemble": 7.171,
    "Cosine_Similarity_±_SD_↑_WM18∗": 11.4
  },
  {
    "test_Condition": "Unseen Modifiers",
    "Cosine_Similarity_±_SD_↑_RGB": 13.288,
    "Cosine_Similarity_±_SD_↑_WM18": 13.891,
    "Cosine_Similarity_±_SD_↑_HSV": 14.183,
    "Cosine_Similarity_±_SD_↑_Ensemble": 10.927,
    "Cosine_Similarity_±_SD_↑_WM18∗": 10.5
  },
  {
    "test_Condition": "Fully Unseen",
    "Cosine_Similarity_±_SD_↑_RGB": 13.859,
    "Cosine_Similarity_±_SD_↑_WM18": 14.516,
    "Cosine_Similarity_±_SD_↑_HSV": 12.432,
    "Cosine_Similarity_±_SD_↑_Ensemble": 13.448,
    "Cosine_Similarity_±_SD_↑_WM18∗": 15.9
  },
  {
    "test_Condition": "Overall",
    "Cosine_Similarity_±_SD_↑_RGB": 5.412,
    "Cosine_Similarity_±_SD_↑_WM18": 5.595,
    "Cosine_Similarity_±_SD_↑_HSV": 7.487,
    "Cosine_Similarity_±_SD_↑_Ensemble": 5.777,
    "Cosine_Similarity_±_SD_↑_WM18∗": 6.8
  }
]
