[
    {
        "_method": " Previous Methods",
        "bas.": "",
        "blo.": "",
        "cal.": "",
        "hou.": "",
        "pub.": "",
        "rec.": "",
        "res.": "",
        "soc.": "",
        "_avg.": ""
    },
    {
        "_method": "Han ( 2018 )",
        "bas.": "88.2",
        "blo.": "61.4",
        "cal.": "81.5",
        "hou.": "74.1",
        "pub.": "80.7",
        "rec.": "82.9",
        "res.": "80.7",
        "soc.": "82.1",
        "_avg.": "79.0"
    },
    {
        "_method": "Su and Yan ( 2017 )",
        "bas.": "88.2",
        "blo.": "62.2",
        "cal.": "82.1",
        "hou.": "78.8",
        "pub.": "80.1",
        "rec.": "86.1",
        "res.": "83.7",
        "soc.": "83.1",
        "_avg.": "80.6"
    },
    {
        "_method": "Herzig and Berant ( 2017 )",
        "bas.": "86.2",
        "blo.": "62.7",
        "cal.": "82.1",
        "hou.": "78.3",
        "pub.": "80.7",
        "rec.": "82.9",
        "res.": "82.2",
        "soc.": "81.7",
        "_avg.": "79.6"
    },
    {
        "_method": " Our Methods",
        "bas.": "",
        "blo.": "",
        "cal.": "",
        "hou.": "",
        "pub.": "",
        "rec.": "",
        "res.": "",
        "soc.": "",
        "_avg.": ""
    },
    {
        "_method": "Shaw et al. ( 2019 )",
        "bas.": " 89.3",
        "blo.": "63.7",
        "cal.": "81.5",
        "hou.": "82.0",
        "pub.": "80.7",
        "rec.": "85.6",
        "res.": "89.5",
        "soc.": "84.8",
        "_avg.": "82.1"
    },
    {
        "_method": "G-R (Beam-10)",
        "bas.": "88.7",
        "blo.": "66.4",
        "cal.": "83.3",
        "hou.": "82.5",
        "pub.": "78.9",
        "rec.": "86.6",
        "res.": "89.8",
        "soc.": "83.7",
        "_avg.": "82.5"
    },
    {
        "_method": "G-R (Beam-10 & pQ)",
        "bas.": "89.0",
        "blo.": "65.2",
        "cal.": "83.3",
        "hou.": "83.6",
        "pub.": "78.3",
        "rec.": "87.5",
        "res.": "89.5",
        "soc.": "85.5",
        "_avg.": "82.7"
    },
    {
        "_method": "G-R (Beam-25)",
        "bas.": "89.0",
        "blo.": " 67.7",
        "cal.": "83.3",
        "hou.": " 84.1",
        "pub.": " 82.6",
        "rec.": "87.5",
        "res.": "89.4",
        "soc.": "83.9",
        "_avg.": "83.4"
    },
    {
        "_method": "G-R (Beam-25 & pQ)",
        "bas.": " 89.3",
        "blo.": "66.7",
        "cal.": "84.5",
        "hou.": "83.6",
        "pub.": "80.1",
        "rec.": " 88.0",
        "res.": " 91.0",
        "soc.": "85.2",
        "_avg.": "83.5"
    },
    {
        "_method": "G-R (Beam-25 & pQ & TH1)",
        "bas.": "89.0",
        "blo.": "65.7",
        "cal.": " 85.1",
        "hou.": "83.6",
        "pub.": "81.4",
        "rec.": " 88.0",
        "res.": " 91.0",
        "soc.": " 86.0",
        "_avg.": " 83.7"
    },
    {
        "_method": "G-R (Beam-25 & pQ & TH2)",
        "bas.": "88.7",
        "blo.": "66.4",
        "cal.": "82.7",
        "hou.": "83.1",
        "pub.": "82.0",
        "rec.": "87.0",
        "res.": "89.8",
        "soc.": "85.8",
        "_avg.": "83.2"
    }
]